fecom/README.md
fecom/__init__.py
fecom/experiment/__init__.py
fecom/experiment/analysis.py
fecom/experiment/data.py
fecom/experiment/experiment_kinds.py
fecom/experiment/experiments.py
fecom/experiment/plot.py
fecom/experiment/rq1_analysis.py
fecom/experiment/run.py
fecom/measurement/README.md
fecom/measurement/__init__.py
fecom/measurement/cpu_temperature.py
fecom/measurement/execution.py
fecom/measurement/idle_stats.py
fecom/measurement/measurement_config.py
fecom/measurement/measurement_parse.py
fecom/measurement/stable_check.py
fecom/measurement/start_measurement.py
fecom/measurement/utilities.py
fecom/patching/README.md
fecom/patching/__init__.py
fecom/patching/client.log
fecom/patching/method_level_patch_imports.py
fecom/patching/method_level_script_patcher.py
fecom/patching/patching_config.py
fecom/patching/project_level_patch_imports.py
fecom/patching/project_level_script_patcher.py
fecom/patching/repo-patching.py
fecom-1.0.0.dist-info/LICENSE
fecom-1.0.0.dist-info/WHEEL
fecom-1.0.0.dist-info/METADATA
fecom-1.0.0.dist-info/RECORD
