Metadata-Version: 2.1
Name: fecom
Version: 1.0.0
Summary: FECoM (Fine-Grained Energy Consumption Measurement) is a Python framework for fine-grained energy measurement in deep learning projects. It provides tools and utilities to accurately measure and analyze energy consumption at the method-level granularity within deep learning code.
Author-email: Saurabhsingh Rajput <saurabh@dal.ca>
Classifier: License :: OSI Approved :: GNU General Public License v3 or later (GPLv3+)
